<?xml version="1.0" encoding="utf-8"?><!DOCTYPE nta PUBLIC '-//Uppaal Team//DTD Flat System 1.1//EN' 'http://www.it.uu.se/research/group/darts/uppaal/flat-1_1.dtd'><nta><declaration>// Place global declarations here.

clock y;
chan b;
chan a;
</declaration><template><name x="5" y="5">Property</name><location id="id0" x="-784" y="-192"><name x="-794" y="-222">Final0</name></location><location id="id1" x="-684" y="-192"><name x="-694" y="-222">Final1</name></location><location id="id2" x="-584" y="-192"><name x="-594" y="-222">Final2</name></location><location id="id3" x="-484" y="-192"><name x="-494" y="-222">Final3</name></location><location id="id4" x="-384" y="-192"><name x="-394" y="-222">Final4</name></location><location id="id5" x="-284" y="-192"><name x="-294" y="-222">Final5</name></location><location id="id6" x="-184" y="-192"><name x="-194" y="-222">Final6</name></location><location id="id7" x="-84" y="-192"><name x="-94" y="-222">NAcc</name></location><init ref="id0"/><transition><source ref="id0"/><target ref="id0"/><label kind="synchronisation" x="-844" y="-207">a?</label><nail x="-814" y="-222"/><nail x="-754" y="-222"/></transition><transition><source ref="id0"/><target ref="id0"/><label kind="guard" x="-844" y="-222">y&gt;=300</label><label kind="synchronisation" x="-844" y="-207">b?</label><label kind="assignment" x="-844" y="-192">y=0</label><nail x="-814" y="-222"/><nail x="-754" y="-222"/></transition><transition><source ref="id0"/><target ref="id1"/><label kind="guard" x="-794" y="-222">y&lt;300</label><label kind="synchronisation" x="-794" y="-207">b?</label></transition><transition><source ref="id1"/><target ref="id1"/><label kind="synchronisation" x="-744" y="-207">a?</label><nail x="-714" y="-222"/><nail x="-654" y="-222"/></transition><transition><source ref="id1"/><target ref="id0"/><label kind="guard" x="-794" y="-222">y&gt;=300</label><label kind="synchronisation" x="-794" y="-207">b?</label><label kind="assignment" x="-794" y="-192">y=0</label></transition><transition><source ref="id1"/><target ref="id2"/><label kind="guard" x="-694" y="-222">y&lt;300</label><label kind="synchronisation" x="-694" y="-207">b?</label></transition><transition><source ref="id2"/><target ref="id2"/><label kind="synchronisation" x="-644" y="-207">a?</label><nail x="-614" y="-222"/><nail x="-554" y="-222"/></transition><transition><source ref="id2"/><target ref="id0"/><label kind="guard" x="-744" y="-222">y&gt;=300</label><label kind="synchronisation" x="-744" y="-207">b?</label><label kind="assignment" x="-744" y="-192">y=0</label></transition><transition><source ref="id2"/><target ref="id3"/><label kind="guard" x="-594" y="-222">y&lt;300</label><label kind="synchronisation" x="-594" y="-207">b?</label></transition><transition><source ref="id3"/><target ref="id3"/><label kind="synchronisation" x="-544" y="-207">a?</label><nail x="-514" y="-222"/><nail x="-454" y="-222"/></transition><transition><source ref="id3"/><target ref="id0"/><label kind="guard" x="-694" y="-222">y&gt;=300</label><label kind="synchronisation" x="-694" y="-207">b?</label><label kind="assignment" x="-694" y="-192">y=0</label></transition><transition><source ref="id3"/><target ref="id4"/><label kind="guard" x="-494" y="-222">y&lt;300</label><label kind="synchronisation" x="-494" y="-207">b?</label></transition><transition><source ref="id4"/><target ref="id4"/><label kind="synchronisation" x="-444" y="-207">a?</label><nail x="-414" y="-222"/><nail x="-354" y="-222"/></transition><transition><source ref="id4"/><target ref="id0"/><label kind="guard" x="-644" y="-222">y&gt;=300</label><label kind="synchronisation" x="-644" y="-207">b?</label><label kind="assignment" x="-644" y="-192">y=0</label></transition><transition><source ref="id4"/><target ref="id5"/><label kind="guard" x="-394" y="-222">y&lt;300</label><label kind="synchronisation" x="-394" y="-207">b?</label></transition><transition><source ref="id5"/><target ref="id5"/><label kind="synchronisation" x="-344" y="-207">a?</label><nail x="-314" y="-222"/><nail x="-254" y="-222"/></transition><transition><source ref="id5"/><target ref="id0"/><label kind="guard" x="-594" y="-222">y&gt;=300</label><label kind="synchronisation" x="-594" y="-207">b?</label><label kind="assignment" x="-594" y="-192">y=0</label></transition><transition><source ref="id5"/><target ref="id6"/><label kind="guard" x="-294" y="-222">y&lt;300</label><label kind="synchronisation" x="-294" y="-207">b?</label></transition><transition><source ref="id6"/><target ref="id6"/><label kind="synchronisation" x="-244" y="-207">a?</label><nail x="-214" y="-222"/><nail x="-154" y="-222"/></transition><transition><source ref="id6"/><target ref="id0"/><label kind="guard" x="-544" y="-222">y&gt;=300</label><label kind="synchronisation" x="-544" y="-207">b?</label><label kind="assignment" x="-544" y="-192">y=0</label></transition><transition><source ref="id6"/><target ref="id7"/><label kind="guard" x="-194" y="-222">y&lt;300</label><label kind="synchronisation" x="-194" y="-207">b?</label></transition><transition><source ref="id7"/><target ref="id7"/><label kind="synchronisation" x="-144" y="-207">a?</label><nail x="-114" y="-222"/><nail x="-54" y="-222"/></transition><transition><source ref="id7"/><target ref="id7"/><label kind="synchronisation" x="-144" y="-207">b?</label><nail x="-114" y="-222"/><nail x="-54" y="-222"/></transition></template><system>// Place template instantiations here.
Process1 = Property();



// List one or more processes to be composed into a system.
system Process1;</system></nta>